whatthepatch/__init__.py
whatthepatch/apply.py
whatthepatch/exceptions.py
whatthepatch/patch.py
whatthepatch/snippets.py
whatthepatch_graingert-0.0.6.dist-info/DESCRIPTION.rst
whatthepatch_graingert-0.0.6.dist-info/METADATA
whatthepatch_graingert-0.0.6.dist-info/RECORD
whatthepatch_graingert-0.0.6.dist-info/WHEEL
whatthepatch_graingert-0.0.6.dist-info/metadata.json
whatthepatch_graingert-0.0.6.dist-info/top_level.txt
